onevox/__init__.py
onevox/cli.py
onevox/io.py
onevox/noise.py
onevox/pipeline.py
onevox/resources/oneVoxel.json
onevox/resources/invocations/invocation_apply.json
onevox/resources/invocations/invocation_clean.json
onevox/resources/invocations/invocation_gen.json
onevox-0.3.0rc3.dist-info/LICENSE
onevox-0.3.0rc3.dist-info/METADATA
onevox-0.3.0rc3.dist-info/WHEEL
onevox-0.3.0rc3.dist-info/entry_points.txt
onevox-0.3.0rc3.dist-info/top_level.txt
onevox-0.3.0rc3.dist-info/RECORD
