Metadata-Version: 2.1
Name: onevox
Version: 0.3.0rc3
Summary: Library for adding well described noise to images.
Home-page: http://github.com/gkiar/onevoxel
Author: Gregory Kiar
Author-email: gkiar07@gmail.com
License: MIT
Platform: UNKNOWN
Classifier: Programming Language :: Python
Classifier: Programming Language :: Python :: 2
Classifier: Programming Language :: Python :: 3
Classifier: Programming Language :: Python :: 2.6
Classifier: Programming Language :: Python :: 2.7
Classifier: Programming Language :: Python :: 3.4
Classifier: Programming Language :: Python :: 3.5
Classifier: Programming Language :: Python :: 3.6
Classifier: Programming Language :: Python :: 3.7
Classifier: Programming Language :: Python :: Implementation :: PyPy
Classifier: License :: OSI Approved :: MIT License
Classifier: Operating System :: OS Independent
Classifier: Natural Language :: English
Requires-Dist: numpy
Requires-Dist: scipy
Requires-Dist: nibabel
Requires-Dist: nilearn
Requires-Dist: scikit-learn
